[
	{
		"name": "Retromc",
		"ip": "https://node.johnymuffin.com/request/retromc",
		"type": "JSON",
		"color":"#00ffe9",
		"category": "minigames"
	},
	{
		"name": "Betalands - Towny",
		"ip": "https://node.johnymuffin.com/request/betalands",
		"type": "JSON",
		"color":"#ff00f6",
		"category": "minigames"
	},
	{
		"name": "Betalands - Anarchy",
		"ip": "http://node.johnymuffin.com/request/betalandsanarchy",
		"type": "JSON",
		"color":"#ff00f6",
		"category": "minigames"
	},
	{
		"name": "Old Haven",
		"ip": "http://node.johnymuffin.com/request/oldhaven2",
		"type": "JSON",
		"color":"#00FF00",
		"category": "minigames"
	},
	{
		"name": "BasCraft",
		"ip": "http://node.johnymuffin.com/request/bascraft",
		"type": "JSON",
		"color":"#ff00f6",
		"category": "minigames"
	},
	{
		"name": "Iceberg Craft",
		"ip": "http://node.johnymuffin.com/request/icebergcraft",
		"type": "JSON",
		"color":"#005cf2",
		"category": "minigames"
	},
	{
		"name": "New Frontier Craft",
		"ip": "https://node.johnymuffin.com/request/NFC",
		"type": "JSON",
		"color":"#045FB4",
		"category": "minigames"
	},
	{
		"name": "AetherMP",
		"ip": "https://node.johnymuffin.com/request/AetherMP",
		"type": "JSON",
		"color":"#D61D00",
		"category": "minigames"
	},
	{
		"name": "Ausbeta",
		"ip": "https://node.johnymuffin.com/request/ausbeta",
		"type": "JSON",
		"color":"#f2930e",
		"category": "minigames"
	},
	{
		"name": "Alpha Place",
		"ip": "https://node.johnymuffin.com/request/alphaplace",
		"type": "JSON",
		"color":"#ba0000",
		"category": "minigames"
	},
	{
		"name": "Retro Lands - TEMP",
		"ip": "https://node.johnymuffin.com/request/retrolandsmodern",
		"type": "JSON",
		"color":"#00ffe9",
		"category": "minigames"
	},
	{
		"name": "Puucraft",
		"ip": "https://betadynmap.puucraft.net/standalone/dynmap_world.json",
		"type": "DYNMAP",
		"color":"#b5cf59",
		"category": "minigames"
	},
	{
		"name": "Always Alpha",
		"ip": "https://node.johnymuffin.com/request/alwaysalpha2",
		"type": "JSON",
		"color":"#edd209",
		"category": "minigames"
	}
]
